src/__init__.py
src/main.py
src/cli/__init__.py
src/cli/agent.py
src/cli/main.py
src/core/__init__.py
src/core/auto_doc_git.py
src/core/auto_docs.py
src/core/auto_engine.py
src/core/auto_git_sync.py
src/core/auto_retry.py
src/core/brain_engine.py
src/core/daemon.py
src/core/detector.py
src/core/doc_generator.py
src/core/exception_handler.py
src/core/git.py
src/core/git_monitor.py
src/core/phase_advance.py
src/core/signoff.py
src/core/state_machine.py
src/core/state_manager.py
src/core/supervisor.py
src/core/task_executor.py
src/core/workflow.py
src/utils/__init__.py
src/utils/date.py
src/utils/file.py
src/utils/lock.py
src/utils/yaml.py
opencode_collaboration-2.0.0.dist-info/METADATA
opencode_collaboration-2.0.0.dist-info/WHEEL
opencode_collaboration-2.0.0.dist-info/entry_points.txt
opencode_collaboration-2.0.0.dist-info/top_level.txt
opencode_collaboration-2.0.0.dist-info/RECORD
