Metadata-Version: 2.4
Name: opencode-collaboration
Version: 2.0.0
Summary: 双Agent协作框架 - 产品经理与开发的分离式协作工具
Author-email: OpenCode <dev@opencode.ai>
License: MIT
Keywords: collaboration,agent,project-management,cli
Classifier: Development Status :: 3 - Alpha
Classifier: Intended Audience :: Developers
Classifier: License :: OSI Approved :: MIT License
Classifier: Programming Language :: Python :: 3
Classifier: Programming Language :: Python :: 3.8
Classifier: Programming Language :: Python :: 3.9
Classifier: Programming Language :: Python :: 3.10
Classifier: Programming Language :: Python :: 3.11
Classifier: Programming Language :: Python :: 3.12
Requires-Python: >=3.8
Requires-Dist: click>=8.0
Requires-Dist: pyyaml>=6.0
Requires-Dist: jinja2>=3.0
Requires-Dist: rich>=12.0
Requires-Dist: inquirer>=2.0
Provides-Extra: dev
Requires-Dist: pytest>=7.0; extra == "dev"
Requires-Dist: pytest-cov>=4.0; extra == "dev"
Requires-Dist: black>=23.0; extra == "dev"
Requires-Dist: flake8>=6.0; extra == "dev"
